{
    "description": "Cuboid Sandstorm is an Iranian threat actor that targeted an Israel-based IT company in July 2021. They gained access to the company's network and used it to compromise downstream customers in the defense, energy, and legal sectors in Israel. The group also utilized custom implants, including a remote access Trojan disguised as RuntimeBroker.exe or svchost.exe, to establish persistence on victim hosts.",
    "meta": {
        "country": "IR",
        "refs": [
            "https://www.microsoft.com/security/blog/2021/11/18/iranian-targeting-of-it-sector-on-the-rise/"
        ],
        "synonyms": [
            "DEV-0228"
        ]
    },
    "uuid": "a4004712-f74b-4c8c-b1fb-bb7229bc2da1",
    "value": "Cuboid Sandstorm"
}