{
    "description": "Earth Wendigo is a threat actor from China that has been targeting several organizations \u2014 including government organizations, research institutions, and universities in Taiwan \u2014 since May 2019, aiming to exfiltrate emails from targeted organizations via the injection of JavaScript backdoors to a webmail system that is widely used in Taiwan. The threat actor also sent spear-phishing emails embedded with malicious links to multiple individuals, including politicians and activists, who support movements in Tibet, the Uyghur region, or Hong Kong.",
    "meta": {
        "cfr-suspected-victims": [
            "Hong Kong",
            "Taiwan"
        ],
        "cfr-target-category": [
            "Government",
            "Education"
        ],
        "country": "CN",
        "refs": [
            "https://www.trendmicro.com/en_us/research/21/a/earth-wendigo-injects-javascript-backdoor-to-service-worker-for-.html"
        ]
    },
    "uuid": "c96e1329-cf7e-44ac-a3db-9e251dc98ec5",
    "value": "Earth Wendigo"
}