{
    "description": "WIP19 is a Chinese-speaking threat group involved in espionage targeting the Middle East and Asia. They utilize a stolen certificate to sign their malware, including SQLMaggie, ScreenCap, and a credential dumper. The group has been observed targeting telecommunications and IT service providers, using toolsets authored by WinEggDrop. WIP19's activities suggest they are after specific information and are part of the broader Chinese espionage landscape.",
    "meta": {
        "country": "CN",
        "refs": [
            "https://www.sentinelone.com/labs/wip19-espionage-new-chinese-apt-targets-it-service-providers-and-telcos-with-signed-malware/"
        ]
    },
    "uuid": "21bb2dab-4125-4ae8-8966-c7381659e180",
    "value": "WIP19"
}